wdwapp/__init__.py
wdwapp/alembic.ini
wdwapp/cron.py
wdwapp/development.ini
wdwapp/initialize_db.py
wdwapp/models.py
wdwapp/production.ini
wdwapp/security.py
wdwapp/sms_handler.py
wdwapp/views.py
wdwapp/alembic/env.py
wdwapp/alembic/script.py.mako
wdwapp/alembic/versions/baa78950306e_version_0_1_0.py
wdwapp/static/Clock-Green.png
wdwapp/static/Clock-Red.png
wdwapp/static/bat-KO.png
wdwapp/static/bat-OK.png
wdwapp/static/favicon.png
wdwapp/templates/detail.pt
wdwapp/templates/layout.pt
wdwapp/templates/overview.pt
wdwapp/templates/old/home.pt
wdwapp/templates/old/sensor_p.pt
wdwapp-0.1.4.dist-info/LICENSE.txt
wdwapp-0.1.4.dist-info/METADATA
wdwapp-0.1.4.dist-info/WHEEL
wdwapp-0.1.4.dist-info/entry_points.txt
wdwapp-0.1.4.dist-info/top_level.txt
wdwapp-0.1.4.dist-info/RECORD
