Metadata-Version: 2.1
Name: wdwapp
Version: 0.1.4
Summary: Webapps for recording and displaying weather data
Home-page: https://github.com/fkieber/wdwapp
Author: Frédéric KIEBER
Author-email: contact@frkb.fr
License: MIT
Keywords: webapp wdwsrv weather
Platform: UNKNOWN
Classifier: Development Status :: 3 - Alpha
Classifier: Environment :: Web Environment
Classifier: Intended Audience :: End Users/Desktop
Classifier: Framework :: Pyramid
Classifier: License :: OSI Approved :: MIT License
Classifier: Natural Language :: English
Classifier: Operating System :: OS Independent
Classifier: Programming Language :: Python :: 3
Classifier: Topic :: Internet :: WWW/HTTP
Classifier: Topic :: Internet :: WWW/HTTP :: WSGI :: Application
Classifier: Topic :: Scientific/Engineering :: Atmospheric Science
License-File: LICENSE.txt
Requires-Dist: pyramid
Requires-Dist: pyramid-chameleon
Requires-Dist: deform
Requires-Dist: sqlalchemy
Requires-Dist: pyramid-tm
Requires-Dist: gunicorn
Requires-Dist: zope.sqlalchemy
Requires-Dist: mysqlclient
Requires-Dist: meteocalc
Requires-Dist: requests
Requires-Dist: bcrypt
Requires-Dist: alembic
